[
  {
    "id": "1",
    "title": "Оливье классический",
    "ingredients": "Картофель 4 шт, морковь 2 шт, яйца 4 шт, докторская колбаса 300 г, солёные огурцы 3 шт, зелёный горошек 1 банка, майонез 200 г, соль, перец, зелень",
    "instructions": "1. Картофель, морковь и яйца отварить, остудить и очистить. 2. Нарезать кубиками картофель, морковь, яйца, колбасу и огурцы. 3. Смешать все ингредиенты с горошком, добавить майонез, посолить и поперчить, перемешать. 4. Украсить зеленью и подавать охлаждённым.",
    "holiday_id": "1", 
    "product_id": "7",
    "cooking_time": "60",
    "budget_level": "бюджетный",
    "image_url": "https://cdn.food.ru/unsigned/fit/640/480/ce/0/czM6Ly9tZWRpYS9waWN0dXJlcy8yMDI1MDExNy8zbmJ4VVcuanBlZw.jpg"
  },
  {
    "id": "2",
    "title": "Салат «Селёдка под шубой»",
    "ingredients": "Свёкла 2 шт, картофель 3 шт, морковь 2 шт, сельдь 1 шт, лук 1 шт, яйца 3 шт, майонез 200 г",
    "instructions": "1. Свёклу, картофель, морковь и яйца отварить, остудить и очистить. 2. Все овощи натереть по отдельности на крупной тёрке. 3. Сельдь нарезать кубиками, лук мелко порубить. 4. Выложить слоями: картофель, чуть майонеза, сельдь, лук, морковь, яйца, свёкла. Каждый слой промазать майонезом. 5. Дать салату настояться в холодильнике 2-3 часа.",
    "holiday_id": "1", 
    "product_id": "7",
    "cooking_time": "90",
    "budget_level": "бюджетный",
    "image_url": "https://e3.edimdoma.ru/system/images/contents/0001/4812/popup/imgonline-com-ua-Compressed-0FMPIIAtk27G0E.jpg?1768915795"
  },
  {
    "id": "3",
    "title": "Кутья рождественская",
    "ingredients": "Пшеница 200 г, мак 50 г, орехи 50 г, изюм 50 г, мёд 2 ст.л., вода",
    "instructions": "1. Пшеницу промыть, залить водой и варить до готовности (примерно 1 час). 2. Мак залить кипятком, затем растереть. 3. Орехи порубить. 4. Смешать пшеницу, мак, орехи, изюм и мёд. Охладить перед подачей.",
    "holiday_id": "2", 
    "product_id": "18",
    "cooking_time": "90",
    "budget_level": "бюджетный",
    "image_url": "https://retro.ua/wp-content/uploads/2025/12/koly-varyat-kutyu.jpg"
  },
  {
    "id": "4",
    "title": "Вареники с вишней",
    "ingredients": "Вишня 250 г, мука 300 г, вода 120 мл, яйцо 1 шт, сахар 50 г, соль",
    "instructions": "1. Замесить тесто из муки, яйца, воды и соли. 2. Раскатать пласт, вырезать кружочки. 3. В середину каждого положить вишню и немного сахара. 4. Слепить аккуратно вареники. 5. Варить в кипящей воде до всплытия. Подавать со сметаной.",
    "holiday_id": "2", 
    "product_id": "11",
    "cooking_time": "50",
    "budget_level": "бюджетный",
    "image_url": "https://avatars.mds.yandex.net/get-vertis-journal/4469561/c36dc3b6-21cb-400c-a8fc-419f242d8ad2.jpg/1600x1600"
  },
  {
    "id": "5",
    "title": "Блины на Масленицу",
    "ingredients": "Молоко 500 мл, яйца 3 шт, мука 200 г, сахар 1 ст.л, соль щепотка, масло растительное 2 ст.л",
    "instructions": "1. Яйца взбить с сахаром и солью. 2. Добавить молоко, перемешать. 3. Постепенно всыпать муку, размешивая до однородности. 4. Добавить масло. 5. Жарить на раскалённой сковороде с двух сторон.",
    "holiday_id": "5", 
    "product_id": "15",
    "cooking_time": "30",
    "budget_level": "бюджетный",
    "image_url": "https://avatars.mds.yandex.net/i?id=904331400fd823de2b0407fae78b2224_l-5879173-images-thumbs&n=13"
  },
  {
    "id": "6",
    "title": "Сырники творожные",
    "ingredients": "Творог 350 г, яйцо 1 шт, сахар 3 ст.л., мука 70 г, соль, масло для жарки",
    "instructions": "1. В миске смешайте творог, яйцо, сахар, щепотку соли и муку. 2. Сформируйте сырники. 3. Обжарьте на среднем огне до золотистой корочки с двух сторон. 4. Подавайте со сметаной или вареньем.",
    "holiday_id": "5", 
    "product_id": "14",
    "cooking_time": "25",
    "budget_level": "бюджетный",
    "image_url": "https://i.ytimg.com/vi/ScP4xyvoX8A/maxresdefault.jpg"
  },
  {
    "id": "7",
    "title": "Кулич классический",
    "ingredients": "Мука 500 г, молоко 200 мл, яйца 3 шт, дрожжи 10 г, сахар 150 г, масло сливочное 100 г, изюм 100 г, ванилин",
    "instructions": "1. В тёплом молоке растворить дрожжи и 1 ст.л. сахара, оставить на 15 минут. 2. Добавить яйца, сахар, растопленное масло, ванилин, муку. Замесить тесто. 3. Добавить изюм, дать подняться в тепле. 4. Разложить по формам, выпекать при 180°C 40 минут. 5. Остудить, украсить глазурью.",
    "holiday_id": "9", 
    "product_id": "15",
    "cooking_time": "120",
    "budget_level": "средний",
    "image_url": "https://www.koolinar.ru/all_image/article/6/6503/article-e0b8262c-fbd5-4090-89e1-618456e4d586_large.jpg"
  },
  {
    "id": "8",
    "title": "Пасхальные яйца (крашенки)",
    "ingredients": "Яйца 10 шт, луковая шелуха, соль, уксус, вода",
    "instructions": "1. Вымыть яйца, положить их в кастрюлю с луковой шелухой. 2. Добавить воду, так чтобы покрывала яйца. 3. Всыпать соль и немного уксуса. 4. Довести до кипения и варить 10 минут. 5. Достать, промыть, натереть салом для блеска.",
    "holiday_id": "9", 
    "product_id": "15",
    "cooking_time": "25",
    "budget_level": "бюджетный",
    "image_url": "https://img.pravda.ru/image/preview/article/5/7/5/2205575_amp.jpeg"
  },
  {
    "id": "9",
    "title": "Уха рыбная",
    "ingredients": "Рыба 500 г, картофель 3 шт, морковь 1 шт, лук 1 шт, лавровый лист, перец горошком, соль",
    "instructions": "1. Рыбу нарежьте крупными кусками. В кастрюлю налейте 1,5 л воды и доведите до кипения. 2. Добавьте подготовленные овощи, специи, посолите. 3. Варите 15–20 минут до готовности рыбы и овощей. Подавать с зеленью.",
    "holiday_id": "7", 
    "product_id": "19",
    "cooking_time": "40",
    "budget_level": "средний",
    "image_url": "https://i.ytimg.com/vi/VICBNo1E2lA/maxresdefault.jpg"
  },
  {
    "id": "10",
    "title": "Пирог с зелёным луком и яйцом",
    "ingredients": "Зелёный лук 200 г, яйца 3 шт, мука 400 г, молоко 200 мл, дрожжи 10 г, масло, соль",
    "instructions": "1. Замесить тесто из муки, молока, дрожжей и масла. 2. Дать тесту подняться, затем разделить. 3. Сварить яйца, мелко порубить с луком. 4. Выложить начинку, сформировать пирог. 5. Выпекать при 180°C 30 минут.",
    "holiday_id": "7", 
    "product_id": null,
    "cooking_time": "60",
    "budget_level": "бюджетный",
    "image_url": "https://i.ytimg.com/vi/21OzeKcWz-U/maxresdefault.jpg"
  },
  {
    "id": "11",
    "title": "Плов узбекский",
    "ingredients": "Баранина 500 г, рис 400 г, морковь 400 г, лук 2 шт, чеснок 1 головка, масло растительное",
    "instructions": "1. Мясо нарезать кусочками, обжарить в масле. 2. Добавить лук, морковь, жарить 10 минут. 3. Всыпать рис, добавить воду, специи и чеснок. 4. Тушить под крышкой до готовности риса (примерно 30 минут).",
    "holiday_id": "13", 
    "product_id": null,
    "cooking_time": "90",
    "budget_level": "средний",
    "image_url": "https://www.koolinar.ru/all_image/article/4/4294/article-da327d42-99e1-452f-86d9-e5ba41341646_large.jpg"
  },
  {
    "id": "12",
    "title": "Курзе с говядиной",
    "ingredients": "Говядина 400 г, лук 1 шт, мука 350 г, яйцо 1 шт, вода 125 мл, соль, перец",
    "instructions": "1. Готовим тесто из муки, яйца, воды и соли. 2. Говядину мелко нарезать или прокрутить, смешать с луком, солью и перцем. 3. Формируем курзе, варим в кипящей воде 7-10 минут.",
    "holiday_id": "13", 
    "product_id": null,
    "cooking_time": "65",
    "budget_level": "бюджетный",
    "image_url": "https://i.ytimg.com/vi/_ZaNxMRdGV4/maxresdefault.jpg"
  },
  {
    "id": "13",
    "title": "Бараньи шашлыки",
    "ingredients": "Баранина 800 г, лук 2 шт, уксус 2 ст. л., соль, перец, специи по вкусу",
    "instructions": "1. Мясо нарезать на куски, посолить и поперчить. 2. Лук нарезать кольцами. Перемешать мясо с луком, уксусом и специями. 3. Мариновать минимум 2 часа. 4. Нанизать на шампуры и жарить над углями до румяности.",
    "holiday_id": "13",
    "product_id": null,
    "cooking_time": "120",
    "budget_level": "средний",
    "image_url": "https://images.gastronom.ru/0Kw9TjywO2VuE4mc3rQ6PsHuLBG71q8pyylqXOfNfn0/pr:article-cover-image/g:ce/rs:auto:0:0:0/L2Ntcy9hbGwtaW1hZ2VzL2VmMTRlMjAxLWNhNTEtNGI1MC05ZTg2LWY4YWExZjJlYzc3Mi5qcGc.webp"
  },
  {
    "id": "14",
    "title": "Яблочный пирог",
    "ingredients": "Яблоки 4 шт, мука 250 г, сахар 150 г, яйца 2 шт, масло сливочное 100 г, разрыхлитель 1 ч.л.",
    "instructions": "1. Взбить сахар с яйцами, добавить растопленное масло. 2. Всыпать муку с разрыхлителем, замесить тесто. 3. Яблоки нарезать дольками, выложить в форму. 4. Залить тестом, выпекать 40 мин при 180°C.",
    "holiday_id": "14",
    "product_id": "20",
    "cooking_time": "55",
    "budget_level": "бюджетный",
    "image_url": "https://images.news.ru/2025/07/01/hxX8bdau6XuYFeJsb3hejmSclw4eky2LCxmXecDz_780.png"
  },
  {
    "id": "15",
    "title": "Яблочное варенье",
    "ingredients": "Яблоки 1 кг, сахар 1 кг, лимон 1 шт, вода 200 мл",
    "instructions": "1. Яблоки очистить и нарезать ломтиками. 2. Залить водой, добавить сахар и дольки лимона. 3. Варить на медленном огне 40-50 мин, периодически помешивая.",
    "holiday_id": "14",
    "product_id": "20",
    "cooking_time": "60",
    "budget_level": "бюджетный",
    "image_url": "https://i.ytimg.com/vi/i6O5vfg9vPw/maxresdefault.jpg"
  },
  {
    "id": "16",
    "title": "Печенье с мёдом",
    "ingredients": "Мёд 4 ст. л., мука 300 г, сахар 100 г, сливочное масло 100 г, яйцо 1 шт, сода 0,5 ч.л.",
    "instructions": "1. Растопить масло и мёд, добавить сахар, яйцо, муку и соду. 2. Замесить тесто, скатать шарики. 3. Выложить на противень и выпекать 12–15 мин при 180°C.",
    "holiday_id": "15",
    "product_id": null,
    "cooking_time": "30",
    "budget_level": "бюджетный",
    "image_url": "https://i.pinimg.com/originals/2d/12/34/2d1234bde57ba8e7dc584257edf1b26b.png"
  },
  {
    "id": "17",
    "title": "Квас с мёдом",
    "ingredients": "Вода 3 л, ржаной хлеб 500 г, мёд 4 ст. л., дрожжи 10 г, изюм по вкусу",
    "instructions": "1. Хлеб подсушить, залить кипятком и настоять 5–6 часов. 2. Процедить, добавить дрожжи и сахар, оставить для брожения 8–10 часов. 3. В готовый квас добавить мёд и изюм.",
    "holiday_id": "15",
    "product_id": null,
    "cooking_time": "720",
    "budget_level": "бюджетный",
    "image_url": "https://slavtradition.com/images/svodki/2022/09/11/7.jpg"
  },
  {
    "id": "18",
    "title": "Пирог с орехами",
    "ingredients": "Грецкие орехи 200 г, мука 250 г, сахар 180 г, яйца 3 шт, сливочное масло 100 г",
    "instructions": "1. Взбить яйца с сахаром, добавить масло, муку, вмешать измельчённые орехи. 2. Вылить в форму, выпекать 35–40 мин при 180°C.",
    "holiday_id": "16",
    "product_id": "21",
    "cooking_time": "60",
    "budget_level": "средний",
    "image_url": "https://i.ytimg.com/vi/fkXnMz6LYM0/maxresdefault.jpg"
  },
  {
    "id": "20",
    "title": "Блины на Покров",
    "ingredients": "Молоко 500 мл, яйца 2 шт, мука 250 г, соль, сахар, масло",
    "instructions": "1. Смешать яйца, молоко, соль и сахар. 2. Добавить муку и замесить тесто. 3. Выпекать блины на сковороде с небольшим количеством масла.",
    "holiday_id": "18",
    "product_id": "18",
    "cooking_time": "35",
    "budget_level": "бюджетный",
    "image_url": "https://caoinform.moscow/wp-content/uploads/sites/38/2024/03/bezymyannyj-1-e1710313575778.png"
  },
  {
    "id": "21",
    "title": "Рыба запечённая с картофелем",
    "ingredients": "Рыба 600 г, картофель 4 шт, лук 1 шт, масло растительное, соль, перец",
    "instructions": "1. Картофель нарезать кружочками, рыбу — порционно. 2. Выложить в форму слоями с луком, посолить и поперчить. 3. Запекать при 180°C 45 минут.",
    "holiday_id": "18",
    "product_id": "19",
    "cooking_time": "55",
    "budget_level": "средний",
    "image_url": "https://avatars.mds.yandex.net/i?id=f955f3532a810fe5f6bd7e971a062f3eeb910a68-5885354-images-thumbs&n=13"
  },
  {
    "id": "22",
    "title": "Пироги с капустой",
    "ingredients": "Капуста 400 г, мука 400 г, молоко 200 мл, дрожжи 10 г, яйцо 1 шт, растительное масло, соль",
    "instructions": "1. Замесить тесто из муки, молока, дрожжей, яйца и масла. 2. Капусту потушить, остудить. 3. Сформировать пирожки, начиняя капустой. 4. Выпекать 30 минут при 180°C.",
    "holiday_id": "19",
    "product_id": "13",
    "cooking_time": "70",
    "budget_level": "бюджетный",
    "image_url": "https://i.ytimg.com/vi/Tq0f5Nviefc/maxresdefault.jpg"
  },
  {
    "id": "23",
    "title": "Осенние пироги",
    "ingredients": "Мука 500 г, масло сливочное 100 г, кефир 250 мл, яйца 2 шт, тыква 300 г, сахар, соль",
    "instructions": "1. Замесить песочное тесто из муки, масла, яиц, сахара и кефира. 2. Тыкву натереть и смешать с сахаром. 3. Выложить в тесто, сформировать пироги, выпекать 30 мин при 180°C.",
    "holiday_id": "19",
    "product_id": null,
    "cooking_time": "60",
    "budget_level": "средний",
    "image_url": "https://www.koolinar.ru/all_image/recipes/141/141645/recipe_d7d49149-83c1-47ca-a20f-381ce1990460.jpg"
  },
  {
    "id": "24",
    "title": "Жаркое по-домашнему",
    "ingredients": "Свинина 500 г, картофель 5 шт, лук 2 шт, морковь 1 шт, масло растительное, соль, перец, лавровый лист",
    "instructions": "1. Нарезать мясо кубиками, обжарить на растительном масле. 2. Добавить нарезанный лук и морковь, немного обжарить. 3. Выложить мясо с овощами в жаропрочную форму, добавить нарезанный картофель, соль, перец, лавровый лист, 200 мл воды. 4. Запекать под крышкой 1 час при 180°C.",
    "holiday_id": "1",
    "product_id": "14",
    "cooking_time": "90",
    "budget_level": "средний",
    "image_url": "https://img.povar.ru/main-micro/e7/69/a2/b0/jarkoe_po-derevenski-884114.JPG"
  },
  {
    "id": "25",
    "title": "Тарталетки с крабовым салатом",
    "ingredients": "Крабовые палочки 200 г, яйца 2 шт, кукуруза консервированная 100 г, сыр твёрдый 50 г, майонез, тарталетки 12 шт",
    "instructions": "1. Крабовые палочки, яйца и сыр нарезать мелкими кубиками. 2. Смешать с кукурузой и майонезом. 3. Разложить салат по тарталеткам, украсить зеленью.",
    "holiday_id": "1",
    "product_id": "7",
    "cooking_time": "20",
    "budget_level": "средний",
    "image_url": "https://images.gastronom.ru/ihfkf1FQ5EIQDXkgGTs-SC_SP-WakJOyvzIMfnET5GE/pr:recipe-cover-image/g:ce/rs:auto:0:0:0/L2Ntcy9hbGwtaW1hZ2VzLzU1NjQ1MjY3LTUxYmMtNGFjNC04ODQ3LWY2MWY0NjJiYjEwYi5qcGc.webp"
  },
  {
    "id": "26",
    "title": "Запечённая утиная грудка с медом",
    "ingredients": "Утиная грудка 2 шт, мёд 2 ст. л., соевый соус 2 ст. л., имбирь молотый 0,5 ч. л., чеснок 2 зубчика, соль, перец",
    "instructions": "1. Соединить мёд, соевый соус, тертый чеснок, имбирь, соль и перец. 2. Замариновать утиные грудки на 1 час. 3. Выложить грудки кожей вверх в форму, залить маринадом. 4. Запекать при 200°C 30-35 минут, поливая соком.",
    "holiday_id": "2",
    "product_id": "12",
    "cooking_time": "70",
    "budget_level": "дорогой",
    "image_url": "https://i.ytimg.com/vi/i9VsqFQwSOg/maxresdefault.jpg"
  },
  {
    "id": "27",
    "title": "Пирожки с маком",
    "ingredients": "Мука 400 г, молоко 200 мл, дрожжи 7 г, сахар 60 г, яйцо 1 шт, сливочное масло 50 г, мак 80 г, ванилин, соль",
    "instructions": "1. Замесить дрожжевое тесто из муки, тёплого молока, дрожжей, яйца, сахара, масла, соли, ванилина. 2. Мак проварить с сахаром и размолоть. 3. Тесто разделить на части, в каждую положить маковую начинку. 4. Сформировать пирожки, выпекать при 180°C 20-25 минут.",
    "holiday_id": "2",
    "product_id": "11",
    "cooking_time": "90",
    "budget_level": "бюджетный",
    "image_url": "https://i.ytimg.com/vi/UOsj_X0rRQA/maxresdefault.jpg"
  },
  {
    "id": "28",
    "title": "Щи постные",
    "ingredients": "Капуста 400 г, картофель 2 шт, морковь 1 шт, лук 1 шт, томатная паста 1 ст. л., растительное масло, соль, перец",
    "instructions": "1. В кастрюлю налить 1,5 л воды, довести до кипения, добавить нашинкованную капусту. 2. Мелко нарезать картофель, добавить к капусте. 3. Поджарить на масле лук и морковь, добавить томатную пасту, обжарить. 4. Выложить зажарку в суп, посолить, поперчить, варить до готовности.",
    "holiday_id": "4",
    "product_id": "13",
    "cooking_time": "60",
    "budget_level": "бюджетный",
    "image_url": "https://avatars.mds.yandex.net/i?id=1acb42360c6659182b2ffc8b177e48f4_l-4887196-images-thumbs&n=13"
  },
  {
    "id": "29",
    "title": "Узвар (традиционный напиток на Крещение)",
    "ingredients": "Сухофрукты (яблоки, груши, изюм) 200 г, вода 2 л, сахар 70 г, мёд по вкусу",
    "instructions": "1. Сухофрукты промыть и залить водой. 2. Довести до кипения, варить 20 минут. 3. Добавить сахар, остудить, затем добавить по вкусу мёд. Подавать охлаждённым.",
    "holiday_id": "4",
    "product_id": "15",
    "cooking_time": "40",
    "budget_level": "бюджетный",
    "image_url": "https://yandex-images.clstorage.net/das5b2198/558e9cTgd/iK8KI50KzYbHwxfNzs0X7FuwxHjw_ptypENI3IJAx9R2HXJN4X63tH805S960ua9njSZpZyZxSnlcyWoV3kdGOz2FgfhA5nG2s4njMv4asl30Kk9mOPaR4hqCdCGdJORX3gjXPAam8UOSfGbvlJTCDPZDERlfCxwsUZVsW8BUBkkEkdCpCaF1nvXO6HfQadAzgQ8MHhexw_A23gBCpADLQrtxkWdmmoUY9gd_95Glxh39YSsxYgMjGXG6RXubQQdQMNvAryOKdZLm5_NhymHZFpIxEjwNqfHmN_80RrIn536VSZV5d5OmDOgWatmCgcMD4XM1F0M0ACBJm0BgqmAcczr35KcbiEeG8dbyS9dO-je1LTcBGJbm6TDaFGC_JOZ_gnCIQ1qblyfIKmPfmKfOBcx0CR9gITYuSohMR6VVOmEDwfSJObpYmObp7FXTX-8moAMqMQ-Gz_EszwJgsSH7d6dTi0RCrq4y0yND0pCt-iPsWhASYxcyAXOSSGqDSyB3DMfhgjyLWqDi0fNR7Hj9JIM5BQA2s_3jBMU3RZQT5Ga8ba9cc7ulGdQqTvuekesC3XoWO2A1EShFmU1orGk_VBbg5oIJkXu3w-nob_pr-AqsLy08NLDw0xDUOkGyEc58g0i0RGK0swHwLXP3p7_sBe11FgxMKCgBdIRQeY1lIm4jxsi_DIZhiN31x2bFT-U1qicsFgGTw-U54hBppjfmeLloqFpmp60B6w1Q8pKzxD3beAgwbj8sG3abX0i2SxFdP8TGuRqacLXG6MNj21z4NKUjPiANi-_FE_YHbJIg12azX4B6eoqEL8MlY-iWgckayXwbF0wXLC5OgWVRoHwDQCjk9os-tXaE8NDseshv9CyrJj0ZA5HT0wf9AW6HBvN_oXG5Qlq6qRnMBGnjloz0MM9VOz99ASwjTqhPV7dfJloD5PmGHqF7hNDW1nnSSvcgiQ4vKAip8f4V-yR6hTs"
  },
  {
    "id": "30",
    "title": "Запечённая каша с тыквой",
    "ingredients": "Пшённая крупа 200 г, тыква 300 г, молоко 500 мл, сахар 3 ст. л., сливочное масло 30 г, ваниль",
    "instructions": "1. Тыкву нарезать кубиками, выложить в форму. 2. Крупу промыть, добавить к тыкве. 3. Влить молоко, посолить и добавить сахар, ваниль. 4. Сверху немного масла. 5. Запекать 1 час при 180°C.",
    "holiday_id": "3",
    "product_id": "11",
    "cooking_time": "70",
    "budget_level": "бюджетный",
    "image_url": "https://i.ytimg.com/vi/3BwnrHeNq6o/maxresdefault.jpg"
  },
  {
    "id": "31",
    "title": "Кутья рисовая с сухофруктами",
    "ingredients": "Рис 150 г, изюм 40 г, курага 40 г, чернослив 40 г, мед 1 ст. л., орехи грецкие 30 г",
    "instructions": "1. Рис промыть и сварить до готовности. 2. Сухофрукты нарезать, орехи измельчить. 3. Соединить рис, сухофрукты, орехи, добавить мёд и перемешать. Охладить и подать.",
    "holiday_id": "3",
    "product_id": "18",
    "cooking_time": "45",
    "budget_level": "бюджетный",
    "image_url": "https://i.pinimg.com/originals/68/6c/f3/686cf3f8d8db0a53e6ee54c1b57ecf05.jpg"
  },
  {
    "id": "32",
    "title": "Блины с икрой к Масленице",
    "ingredients": "Молоко 600 мл, яйца 2 шт, мука 300 г, соль, сахар, сливочное масло, красная икра 100 г",
    "instructions": "1. Замесить жидкое тесто из молока, яиц, муки, соли и сахара. 2. Выпечь тонкие блины на сливочном масле. 3. Подавать с красной икрой.",
    "holiday_id": "5",
    "product_id": "9",
    "cooking_time": "45",
    "budget_level": "дорогой",
    "image_url": "https://www.koolinar.ru/all_image/article/5/5786/article-37f962ae-50a7-4c7b-80d9-fab8b8a3d8a9_large.jpg"
  },
  {
    "id": "33",
    "title": "Печёночные оладьи",
    "ingredients": "Куриная печень 400 г, яйца 2 шт, мука 100 г, лук 1 шт, соль, перец, растительное масло",
    "instructions": "1. Печень и лук измельчить в блендере, добавить яйца, муку, соль и перец. 2. Хорошо перемешать массу. 3. Обжарить оладьи на разогретом масле с двух сторон до румяности.",
    "holiday_id": "5",
    "product_id": "8",
    "cooking_time": "35",
    "budget_level": "бюджетный",
    "image_url": "https://i.ytimg.com/vi/ElX7yaiNxCc/maxresdefault.jpg"
  },
  {
    "id": "34",
    "title": "Куриное филе в сливках",
    "ingredients": "Куриное филе 500 г, сливки 200 мл, лук 1 шт, специи, соль, перец, масло растительное",
    "instructions": "1. Куриное филе нарезать и обжарить до золотистой корки. 2. Добавить лук, обжарить. 3. Влить сливки, специи, тушить на слабом огне 20 минут.",
    "holiday_id": "6",
    "product_id": "6",
    "cooking_time": "35",
    "budget_level": "средний",
    "image_url": "https://i.ytimg.com/vi/4ERKydNMc3c/maxresdefault.jpg"
  },
  {
    "id": "35",
    "title": "Гратен из картофеля с сыром",
    "ingredients": "Картофель 600 г, сливки 200 мл, сыр твёрдый 100 г, чеснок 2 зубчика, соль, перец",
    "instructions": "1. Картофель нарезать тонкими пластинами, выложить слоями в форму. 2. Чередовать с измельченным чесноком, солить и перчить. 3. Залить сливками и посыпать тертым сыром. 4. Запекать при 180°C 35-40 минут.",
    "holiday_id": "6",
    "product_id": "17",
    "cooking_time": "60",
    "budget_level": "средний",
    "image_url": "https://images.gastronom.ru/pjECYLf6EY8rDDYK4ma_GBF7cNQoBJ-GGWxwHJ6x1ZY/pr:recipe-cover-image/g:ce/rs:auto:0:0:0/L2Ntcy9hbGwtaW1hZ2VzLzgxMGU4NDdkLTUxODUtNGI5OC05MGU5LTMxOTY0NTcyZTRmOC5qcGc.webp"
  },
  {
    "id": "36",
    "title": "Салат «Весенний»",
    "ingredients": "Редис 6 шт, свежий огурец 1 шт, зелёный лук, укроп, сметана 2 ст. л., соль",
    "instructions": "1. Редис и огурец нарезать кружочками. 2. Мелко порубить зелёный лук и укроп. 3. Всё смешать, посолить и заправить сметаной.",
    "holiday_id": "7",
    "product_id": "2",
    "cooking_time": "10",
    "budget_level": "бюджетный",
    "image_url": "https://images.news.ru/photo/9d91558c-20e1-11f0-bdcd-ac1f6bad3ff4_780.jpg"
  },
  {
    "id": "37",
    "title": "Творожный десерт с клубникой",
    "ingredients": "Творог 200 г, клубника 150 г, сахар 2 ст. л., ваниль, взбитые сливки для украшения",
    "instructions": "1. Клубнику нарезать, посыпать сахаром. 2. Творог взбить с ванилью и половиной клубники. 3. Выложить в креманки слоями творожную массу и оставшуюся клубнику, украсить взбитыми сливками.",
    "holiday_id": "7",
    "product_id": "1",
    "cooking_time": "15",
    "budget_level": "средний",
    "image_url": "https://365news.biz/wp-content/uploads/2020/09/0b31295105d6920231a12ed0e029f0df.jpg"
  }
]